dnora_era5/__init__.py
dnora_era5/_version.py
dnora_era5/modelrun/__init__.py
dnora_era5/modelrun/templates.py
dnora_era5/spectra/__init__.py
dnora_era5/spectra/spectral_readers.py
dnora_era5/waterlevel/__init__.py
dnora_era5/waterlevel/waterlevel_readers.py
dnora_era5/wind/__init__.py
dnora_era5/wind/wind_readers.py
dnora_era5-0.1.0.dist-info/licenses/LICENSE
dnora_era5-0.1.0.dist-info/METADATA
dnora_era5-0.1.0.dist-info/WHEEL
dnora_era5-0.1.0.dist-info/top_level.txt
dnora_era5-0.1.0.dist-info/RECORD
