Metadata-Version: 2.4
Name: dnora-era5
Version: 0.1.0
Summary: Add-on to dnora: Access to ERA5 weather products
Author-email: Konstantinos Christakos <konstantinosc@met.no>, Jan-Victor Björkqvist <janvb@met.no>
License: MIT License
Project-URL: homepage, https://github.com/MET-OM/dnora
Project-URL: download, https://github.com/MET-OM/dnora
Requires-Python: <3.11,>=3.9
License-File: LICENSE
Requires-Dist: dnora>=2.0.4
Requires-Dist: cdsapi>=0.7.6
Provides-Extra: test
Requires-Dist: pytest>=7.0; extra == "test"
Dynamic: license-file
